{
  "player_sprite": {
    "x": 30,
    "y": 390,
    "w": 460,
    "h": 460
  },
  "wild_sprite": {
    "x": 1280,
    "y": 140,
    "w": 420,
    "h": 420
  },
  "enemy_bar": {
    "x": 820,
    "y": 60,
    "w": 580,
    "h": 110
  },
  "player_bar": {
    "x": 620,
    "y": 480,
    "w": 580,
    "h": 110
  },
  "text_box": {
    "x": 660,
    "y": 260,
    "w": 560,
    "h": 180
  },
  "move_1": {
    "x": 610,
    "y": 560,
    "w": 340,
    "h": 120
  },
  "move_2": {
    "x": 970,
    "y": 560,
    "w": 340,
    "h": 120
  },
  "move_3": {
    "x": 1330,
    "y": 560,
    "w": 340,
    "h": 120
  },
  "capture": {
    "x": 610,
    "y": 690,
    "w": 340,
    "h": 90
  },
  "switch": {
    "x": 970,
    "y": 690,
    "w": 340,
    "h": 90
  },
  "enemy_hp_fill": {
    "x": 880,
    "y": 130,
    "w": 470,
    "h": 20
  },
  "player_hp_fill": {
    "x": 680,
    "y": 545,
    "w": 470,
    "h": 20
  },
  "enemy_name": {
    "x": 440,
    "y": 40,
    "w": 0,
    "h": 0
  },
  "player_name": {
    "x": 660,
    "y": 490,
    "w": 0,
    "h": 0
  },
  "player_hp_text": {
    "x": 660,
    "y": 548,
    "w": 0,
    "h": 0
  }
}